Workbook

Sheet 企业信用评级打分表
A1: 企业信用评级打分表（满分100分）
A2: 维度 | B2: 评级指标 | C2: 标准分值 | D2: 评分规则 | E2: 打分 | F2: 实际得分 | G2: 维度权重(%) | H2: 指标权重(%) | I2: 标准化得分(0-100) | J2: 加权得分
A3: 1. 企业基本资质 | B3: 1.1 注册资本与实缴资本 | C3: 8 | D3: 实缴资本≥注册资本100%：8分；实缴资本≥50%且<100%：5分；实缴资本≥20%且<50%：3分；实缴资本<20%：0分 | F3: =MIN(E3, C3) | G3: 0.2 | H3: 0.4 | I3: =IFERROR((F3/C3)*100, 0) | J3: =IFERROR(I3*G3*H3, 0)
B4: 1.2 企业成立年限 | C4: 6 | D4: 成立≥10年：6分；成立≥5年且<10年：4分；成立≥3年且<5年：2分；成立<3年：0分 | F4: =MIN(E4, C4) | G4: 0.2 | H4: 0.3 | I4: =IFERROR((F4/C4)*100, 0) | J4: =IFERROR(I4*G4*H4, 0)
B5: 1.3 资质认证 | C5: 6 | D5: 具备行业甲级/一级资质/高新技术企业认证：6分；具备行业乙级/二级资质：3分；无相关资质：0分 | F5: =MIN(E5, C5) | G5: 0.2 | H5: 0.3 | I5: =IFERROR((F5/C5)*100, 0) | J5: =IFERROR(I5*G5*H5, 0)
A6: 2. 财务健康状况 | B6: 2.1 偿债能力（资产负债率） | C6: 12 | D6: 资产负债率≤50%：12分；50%<资产负债率≤70%：8分；70%<资产负债率≤90%：4分；资产负债率>90%：0分 | F6: =MIN(E6, C6) | G6: 0.3 | H6: 0.4 | I6: =IFERROR((F6/C6)*100, 0) | J6: =IFERROR(I6*G6*H6, 0)
B7: 2.2 盈利能力 | C7: 10 | D7: 近2年连续盈利，净利润增长率≥10%：10分；近2年连续盈利，增长率<10%：6分；近1年盈利1年亏损：3分；近2年连续亏损：0分 | F7: =MIN(E7, C7) | G7: 0.3 | H7: 0.3333 | I7: =IFERROR((F7/C7)*100, 0) | J7: =IFERROR(I7*G7*H7, 0)
B8: 2.3 运营能力（营业周期） | C8: 8 | D8: 营业周期≤行业平均水平：8分；行业平均<营业周期≤1.5倍行业平均：4分；营业周期>1.5倍行业平均：0分 | F8: =MIN(E8, C8) | G8: 0.3 | H8: 0.2667 | I8: =IFERROR((F8/C8)*100, 0) | J8: =IFERROR(I8*G8*H8, 0)
A9: 3. 履约信用记录 | B9: 3.1 合同履约率 | C9: 10 | D9: 近1年合同履约率100%：10分；95%≤履约率<100%：6分；80%≤履约率<95%：3分；履约率<80%：0分 | F9: =MIN(E9, C9) | G9: 0.25 | H9: 0.4 | I9: =IFERROR((F9/C9)*100, 0) | J9: =IFERROR(I9*G9*H9, 0)
B10: 3.2 金融信用记录 | C10: 10 | D10: 近2年无逾期还款记录：10分；1次轻微逾期（已结清）：6分；2次及以上逾期：3分；未结清逾期/不良贷款：0分 | F10: =MIN(E10, C10) | G10: 0.25 | H10: 0.4 | I10: =IFERROR((F10/C10)*100, 0) | J10: =IFERROR(I10*G10*H10, 0)
B11: 3.3 失信与行政处罚 | C11: 5 | D11: 近3年无失信/重大行政处罚：5分；1次一般行政处罚：2分；有失信/重大行政处罚：0分 | F11: =MIN(E11, C11) | G11: 0.25 | H11: 0.2 | I11: =IFERROR((F11/C11)*100, 0) | J11: =IFERROR(I11*G11*H11, 0)
A12: 4. 经营管理能力 | B12: 4.1 营收稳定性 | C12: 8 | D12: 近3年营收复合增长率≥15%：8分；5%≤增长率<15%：5分；0%≤增长率<5%：2分；负增长：0分 | F12: =MIN(E12, C12) | G12: 0.15 | H12: 0.5333 | I12: =IFERROR((F12/C12)*100, 0) | J12: =IFERROR(I12*G12*H12, 0)
B13: 4.2 团队与管理稳定性 | C13: 7 | D13: 核心团队3年无重大变动，流失率≤行业平均：7分；1次团队变动，流失率略高：4分；团队频繁变动，流失率远高：0分 | F13: =MIN(E13, C13) | G13: 0.15 | H13: 0.4667 | I13: =IFERROR((F13/C13)*100, 0) | J13: =IFERROR(I13*G13*H13, 0)
A14: 5. 合规与风险防控 | B14: 5.1 税务与社保合规 | C14: 5 | D14: 近3年无税务违章，社保合规：5分；1次轻微违章（已整改）：2分；重大违章/违规：0分 | F14: =MIN(E14, C14) | G14: 0.1 | H14: 0.5 | I14: =IFERROR((F14/C14)*100, 0) | J14: =IFERROR(I14*G14*H14, 0)
B15: 5.2 风险管理制度 | C15: 5 | D15: 完善的内控与风险管理制度且有效执行：5分；基本制度，执行一般：3分；无制度：0分 | F15: =MIN(E15, C15) | G15: 0.1 | H15: 0.5 | I15: =IFERROR((F15/C15)*100, 0) | J15: =IFERROR(I15*G15*H15, 0)
A16: 总分合计 | F16: =SUM(F3:F15) | I16: 加权总分 | J16: =SUM(J3:J15)

Sheet 评级结果汇总表
A1: 企业信用评级结果汇总表
A2: 企业基本信息
A3: 企业名称
A4: 统一社会信用代码
A5: 成立日期
A6: 注册资本
A7: 所属行业
A9: 评级结果 | C9: 加权评级总分 | D9: ='企业信用评级打分表'!J16
A10: 评级总分 | B10: ='企业信用评级打分表'!F16
A11: 信用等级 | B11: =IF(B10>=90,"AAA",IF(B10>=80,"AA",IF(B10>=70,"A",IF(B10>=60,"BBB",IF(B10>=50,"BB","B")))))
A12: 评级说明 | B12: =IF(B11="AAA","信用优秀，履约能力极强",IF(B11="AA","信用良好，履约能力强",IF(B11="A","信用较好，履约能力较强",IF(B11="BBB","信用一般，履约能力尚可",IF(B11="BB","信用较差，履约能力较弱","信用极差，履约能力极弱")))))
A14: 五大维度得分明细
A15: 维度 | B15: 标准分值 | C15: 实际得分
A16: 企业基本资质 | B16: 20 | C16: =SUM('企业信用评级打分表'!F3:F5)
A17: 财务健康状况 | B17: 30 | C17: =SUM('企业信用评级打分表'!F6:F8)
A18: 履约信用记录 | B18: 25 | C18: =SUM('企业信用评级打分表'!F9:F11)
A19: 经营管理能力 | B19: 15 | C19: =SUM('企业信用评级打分表'!F12:F13)
A20: 合规与风险防控 | B20: 10 | C20: =SUM('企业信用评级打分表'!F14:F15)
A21: 维度合计 | C21: =SUM(C16:C20)
